{
    "max_open_trades": 3,
    "stake_currency": "INR",
    "stake_amount": 10000,
    "tradable_balance_ratio": 0.99,
    "fiat_display_currency": "INR",
    "dry_run": true,
    "dry_run_wallet": 100000,
    "cancel_open_orders_on_exit": false,
    
    "timeframe": "1h",
    
    "exchange": {
        "name": "zerodha",
        "key": "YOUR_ZERODHA_API_KEY",
        "secret": "YOUR_ZERODHA_API_SECRET",
        "password": "PASTE_GENERATED_ACCESS_TOKEN_HERE",
        "ccxt_config": {
            "enableRateLimit": true,
            "rateLimit": 100
        },
        "ccxt_async_config": {
            "enableRateLimit": true,
            "rateLimit": 100
        },
        "pair_whitelist": [
            "NSE:INFY/INR",
            "NSE:TCS/INR",
            "NSE:RELIANCE/INR",
            "NSE:HDFCBANK/INR",
            "NSE:ICICIBANK/INR",
            "NSE:SBIN/INR",
            "NSE:BHARTIARTL/INR",
            "NSE:ITC/INR",
            "NSE:LT/INR",
            "NSE:HINDUNILVR/INR"
        ],
        "pair_blacklist": []
    },
    
    "dataformat_ohlcv": "json",
    "dataformat_trades": "jsongz",
    
    "entry_pricing": {
        "price_side": "same",
        "use_order_book": true,
        "order_book_top": 1,
        "price_last_balance": 0.0,
        "check_depth_of_market": {
            "enabled": false,
            "bids_to_ask_delta": 1
        }
    },
    
    "exit_pricing": {
        "price_side": "same",
        "use_order_book": true,
        "order_book_top": 1
    },
    
    "order_types": {
        "entry": "limit",
        "exit": "limit",
        "emergency_exit": "market",
        "force_exit": "market",
        "force_entry": "market",
        "stoploss": "market",
        "stoploss_on_exchange": false,
        "stoploss_on_exchange_interval": 60,
        "stoploss_on_exchange_limit_ratio": 0.99
    },
    
    "order_time_in_force": {
        "entry": "gtc",
        "exit": "gtc"
    },
    
    "unfilledtimeout": {
        "entry": 10,
        "exit": 10,
        "exit_timeout_count": 0,
        "unit": "minutes"
    },
    
    "pairlists": [
        {
            "method": "StaticPairList"
        }
    ],
    
    "protections": [
        {
            "method": "StoplossGuard",
            "lookback_period_candles": 60,
            "trade_limit": 4,
            "stop_duration_candles": 60,
            "only_per_pair": false
        },
        {
            "method": "MaxDrawdown",
            "lookback_period_candles": 200,
            "trade_limit": 20,
            "stop_duration_candles": 10,
            "max_allowed_drawdown": 0.2
        },
        {
            "method": "LowProfitPairs",
            "lookback_period_candles": 60,
            "trade_limit": 2,
            "stop_duration_candles": 60,
            "required_profit": 0.02
        },
        {
            "method": "CooldownPeriod",
            "stop_duration_candles": 5
        }
    ],
    
    "edge": {
        "enabled": false,
        "process_throttle_secs": 3600,
        "calculate_since_number_of_days": 7,
        "allowed_risk": 0.01,
        "stoploss_range_min": -0.01,
        "stoploss_range_max": -0.1,
        "stoploss_range_step": -0.01,
        "minimum_winrate": 0.60,
        "minimum_expectancy": 0.20,
        "min_trade_number": 10,
        "max_trade_duration_minute": 1440,
        "remove_pumps": false
    },
    
    "telegram": {
        "enabled": false,
        "token": "your_telegram_bot_token",
        "chat_id": "your_telegram_chat_id",
        "notification_settings": {
            "status": "silent",
            "warning": "on",
            "startup": "on",
            "entry": "silent",
            "entry_fill": "on",
            "exit": {
                "roi": "silent",
                "emergency_exit": "on",
                "force_exit": "on",
                "exit_signal": "silent",
                "trailing_stop_loss": "on",
                "stop_loss": "on",
                "stoploss_on_exchange": "on",
                "custom_exit": "silent"
            },
            "exit_fill": "on",
            "protection_trigger": "on",
            "protection_trigger_global": "on"
        }
    },
    
    "api_server": {
        "enabled": true,
        "listen_ip_address": "127.0.0.1",
        "listen_port": 8080,
        "verbosity": "error",
        "enable_openapi": false,
        "jwt_secret_key": "somethingrandom",
        "ws_token": "sametoken",
        "CORS_origins": [],
        "username": "freqtrade",
        "password": "freqtrade"
    },
    
    "bot_name": "Freqtrade-Zerodha-Bot",
    "initial_state": "running",
    "force_entry_enable": false,
    "disable_dataframe_checks": false,
    "strategy": "SimpleRSI_NSE",
    "strategy_path": "user_data/strategies/",
    "db_url": "sqlite:///tradesv3.sqlite",
    "logfile": "logs/freqtrade.log",
    "user_data_dir": "user_data",
    
    "internals": {
        "process_throttle_secs": 5,
        "heartbeat_interval": 60,
        "sd_notify": false
    }
} 